mclone/__init__.py
mclone/fuck_mao.so
mclone/fuck_mao_32.so
mclone/main_fuck.py
mclone-0.0.5.dist-info/LICENSE
mclone-0.0.5.dist-info/METADATA
mclone-0.0.5.dist-info/WHEEL
mclone-0.0.5.dist-info/entry_points.txt
mclone-0.0.5.dist-info/top_level.txt
mclone-0.0.5.dist-info/RECORD
