Metadata-Version: 2.1
Name: mclone
Version: 0.0.5
Summary: Facebook Old Id cloning!
Home-page: https://github.com/mao2116
Author: mao2116
Author-email: mao2116@yandex.com
License: MIT
Keywords: maohacker,fb hack, hacking tool,clone fb,maotool,hack,fb,hack,termux,mclone,cloner,facebook hack,hackmao2116
Platform: UNKNOWN
Classifier: Development Status :: 4 - Beta
Classifier: Intended Audience :: Developers
Classifier: Topic :: Software Development :: Libraries :: Python Modules
Classifier: License :: OSI Approved :: MIT License
Classifier: Programming Language :: Python :: 2
Classifier: Operating System :: OS Independent
Classifier: Environment :: Console
Requires-Python: <=2.7.18
Requires-Dist: lolcat
Requires-Dist: requests
Requires-Dist: mechanize
